fissle/__init__.py
fissle-0.0.4.dist-info/LICENSE
fissle-0.0.4.dist-info/WHEEL
fissle-0.0.4.dist-info/METADATA
fissle-0.0.4.dist-info/RECORD
