Metadata-Version: 2.1
Name: fissle
Version: 0.0.4
Summary: Simple boilerplate for cli scripts
Home-page: https://github.com/d3rp/fissle.git
License: UNKNOWN
Keywords: cli
Author: Joni Turunen
Author-email: rojun.itu@gmail.com
Requires-Python: >=3.5
Classifier: License :: OSI Approved :: MIT License
Requires-Dist: fire==0.1.3
